pyuipc/__init__.pyi
pyuipc/backend.pyi
pyuipc/builtin.pyi
pyuipc/constitution.pyi
pyuipc/core.pyi
pyuipc/diff_sim.pyi
pyuipc/engine.pyi
pyuipc/geometry.pyi
pyuipc/unit.pyi
pyuipc/world.pyi
pyuipc_loader/__init__.py
pyuipc_loader/RelWithDebInfo/bin/fmt.dll
pyuipc_loader/RelWithDebInfo/bin/glfw3.dll
pyuipc_loader/RelWithDebInfo/bin/python311.dll
pyuipc_loader/RelWithDebInfo/bin/pyuipc.cp311-win_amd64.pyd
pyuipc_loader/RelWithDebInfo/bin/spdlog.dll
pyuipc_loader/RelWithDebInfo/bin/uipc_backend_cuda.dll
pyuipc_loader/RelWithDebInfo/bin/uipc_backend_none.dll
pyuipc_loader/RelWithDebInfo/bin/uipc_constitution.dll
pyuipc_loader/RelWithDebInfo/bin/uipc_core.dll
pyuipc_loader/RelWithDebInfo/bin/uipc_geometry.dll
pyuipc_loader/RelWithDebInfo/bin/uipc_io.dll
pyuipc_loader/RelWithDebInfo/bin/uipc_sanity_check.dll
pyuipc_loader/RelWithDebInfo/bin/zlib1.dll
pyuipc_utils/__init__.py
pyuipc_utils/constitution.py
pyuipc_utils/geometry.py
pyuipc_utils/gui.py
pyuipc-0.9.0.dist-info/LICENSE
pyuipc-0.9.0.dist-info/METADATA
pyuipc-0.9.0.dist-info/WHEEL
pyuipc-0.9.0.dist-info/top_level.txt
pyuipc-0.9.0.dist-info/RECORD
