Metadata-Version: 2.1
Name: pyuipc
Version: 0.9.0
Author-email: Zihang Zhu <paradise_craftsman@hotmail.com>
Maintainer-email: Zihang Zhu <paradise_craftsman@hotmail.com>, Lu Xinyu <lxy819469559@gmail.com>
License: GNU GENERAL PUBLIC LICENSE
Project-URL: Homepage, https://spirimirror.github.io/libuipc-doc/
Project-URL: Issues, https://github.com/spiriMirror/libuipc/issues
Keywords: ipc,computer graphics,physics simulation
Requires-Python: >=3.10
License-File: LICENSE
Requires-Dist: numpy
Provides-Extra: gui
Requires-Dist: polyscope; extra == "gui"
